dory.cpython-38-darwin.so
doryrips.cpython-38-darwin.so
doryrips-0.0.9.dist-info/LICENSE
doryrips-0.0.9.dist-info/METADATA
doryrips-0.0.9.dist-info/WHEEL
doryrips-0.0.9.dist-info/top_level.txt
doryrips-0.0.9.dist-info/RECORD
