Metadata-Version: 2.1
Name: doryrips
Version: 0.0.9
Summary: Python interface for the Dory
Home-page: UNKNOWN
Author: Manu Aggarwal
Author-email: manu.aggarwal@nih.gov
License: UNKNOWN
Platform: UNKNOWN
Requires-Python: >=3
